PokerNow/__init__.py
PokerNow/client.py
PokerNow/managers.py
PokerNow/models.py
PokerNow-0.3.5.dist-info/LICENSE
PokerNow-0.3.5.dist-info/METADATA
PokerNow-0.3.5.dist-info/WHEEL
PokerNow-0.3.5.dist-info/top_level.txt
PokerNow-0.3.5.dist-info/RECORD
